pelican_meetup_info.py
pelican_meetup_info-0.0.2.dist-info/DESCRIPTION.rst
pelican_meetup_info-0.0.2.dist-info/METADATA
pelican_meetup_info-0.0.2.dist-info/RECORD
pelican_meetup_info-0.0.2.dist-info/WHEEL
pelican_meetup_info-0.0.2.dist-info/metadata.json
pelican_meetup_info-0.0.2.dist-info/top_level.txt
