Metadata-Version: 2.0
Name: pelican-meetup-info
Version: 0.0.2
Summary: A Pelican plugin that provides group and event information for a meetup.com group.
Home-page: https://github.com/tylerdave/pelican-meetup-info
Author: Dave Forgac
Author-email: tylerdave@tylerdave.com
License: MIT
Keywords: pelican plugin meetup
Platform: UNKNOWN
Classifier: Development Status :: 3 - Alpha
Classifier: Intended Audience :: Developers
Classifier: License :: OSI Approved :: MIT License
Requires-Dist: requests
